{
    "classes": [
        {
            "className": "QRScannerViewModel",
            "lineNumber": 17,
            "methods": [
                {
                    "access": "public",
                    "arguments": [
                        {
                            "name": "camera",
                            "type": "QString"
                        }
                    ],
                    "index": 13,
                    "name": "setSelectedCamera",
                    "returnType": "void"
                },
                {
                    "access": "public",
                    "index": 14,
                    "name": "refreshCameraList",
                    "returnType": "void"
                },
                {
                    "access": "public",
                    "index": 15,
                    "name": "toggleStreaming",
                    "returnType": "void"
                },
                {
                    "access": "public",
                    "arguments": [
                        {
                            "name": "videoSink",
                            "type": "QVideoSink*"
                        }
                    ],
                    "index": 16,
                    "name": "setVideoSink",
                    "returnType": "void"
                }
            ],
            "object": true,
            "properties": [
                {
                    "constant": false,
                    "designable": true,
                    "final": false,
                    "index": 0,
                    "name": "currentDate",
                    "notify": "currentDateChanged",
                    "read": "currentDate",
                    "required": false,
                    "scriptable": true,
                    "stored": true,
                    "type": "QString",
                    "user": false
                },
                {
                    "constant": false,
                    "designable": true,
                    "final": false,
                    "index": 1,
                    "name": "currentTime",
                    "notify": "currentTimeChanged",
                    "read": "currentTime",
                    "required": false,
                    "scriptable": true,
                    "stored": true,
                    "type": "QString",
                    "user": false
                },
                {
                    "constant": false,
                    "designable": true,
                    "final": false,
                    "index": 2,
                    "name": "availableCameras",
                    "notify": "availableCamerasChanged",
                    "read": "availableCameras",
                    "required": false,
                    "scriptable": true,
                    "stored": true,
                    "type": "QStringList",
                    "user": false
                },
                {
                    "constant": false,
                    "designable": true,
                    "final": false,
                    "index": 3,
                    "name": "selectedCamera",
                    "notify": "selectedCameraChanged",
                    "read": "selectedCamera",
                    "required": false,
                    "scriptable": true,
                    "stored": true,
                    "type": "QString",
                    "user": false,
                    "write": "setSelectedCamera"
                },
                {
                    "constant": false,
                    "designable": true,
                    "final": false,
                    "index": 4,
                    "name": "isStreaming",
                    "notify": "isStreamingChanged",
                    "read": "isStreaming",
                    "required": false,
                    "scriptable": true,
                    "stored": true,
                    "type": "bool",
                    "user": false
                },
                {
                    "constant": false,
                    "designable": true,
                    "final": false,
                    "index": 5,
                    "name": "isLoading",
                    "notify": "isLoadingChanged",
                    "read": "isLoading",
                    "required": false,
                    "scriptable": true,
                    "stored": true,
                    "type": "bool",
                    "user": false
                },
                {
                    "constant": false,
                    "designable": true,
                    "final": false,
                    "index": 6,
                    "name": "videoSink",
                    "notify": "videoSinkChanged",
                    "read": "videoSink",
                    "required": false,
                    "scriptable": true,
                    "stored": true,
                    "type": "QVideoSink*",
                    "user": false,
                    "write": "setVideoSink"
                },
                {
                    "constant": false,
                    "designable": true,
                    "final": false,
                    "index": 7,
                    "name": "qrCodeData",
                    "notify": "qrCodeDataChanged",
                    "read": "qrCodeData",
                    "required": false,
                    "scriptable": true,
                    "stored": true,
                    "type": "QString",
                    "user": false
                },
                {
                    "constant": false,
                    "designable": true,
                    "final": false,
                    "index": 8,
                    "name": "qrCodeDataLatest",
                    "notify": "qrCodeDataLatestChanged",
                    "read": "qrCodeDataLatest",
                    "required": false,
                    "scriptable": true,
                    "stored": true,
                    "type": "QString",
                    "user": false
                }
            ],
            "qualifiedClassName": "QRScannerViewModel",
            "signals": [
                {
                    "access": "public",
                    "index": 0,
                    "name": "currentDateChanged",
                    "returnType": "void"
                },
                {
                    "access": "public",
                    "index": 1,
                    "name": "currentTimeChanged",
                    "returnType": "void"
                },
                {
                    "access": "public",
                    "index": 2,
                    "name": "availableCamerasChanged",
                    "returnType": "void"
                },
                {
                    "access": "public",
                    "index": 3,
                    "name": "selectedCameraChanged",
                    "returnType": "void"
                },
                {
                    "access": "public",
                    "index": 4,
                    "name": "isStreamingChanged",
                    "returnType": "void"
                },
                {
                    "access": "public",
                    "index": 5,
                    "name": "isLoadingChanged",
                    "returnType": "void"
                },
                {
                    "access": "public",
                    "arguments": [
                        {
                            "name": "errorMessage",
                            "type": "QString"
                        }
                    ],
                    "index": 6,
                    "name": "cameraErrorOccured",
                    "returnType": "void"
                },
                {
                    "access": "public",
                    "index": 7,
                    "name": "videoSinkChanged",
                    "returnType": "void"
                },
                {
                    "access": "public",
                    "index": 8,
                    "name": "qrCodeDataChanged",
                    "returnType": "void"
                },
                {
                    "access": "public",
                    "index": 9,
                    "name": "qrCodeDataLatestChanged",
                    "returnType": "void"
                }
            ],
            "slots": [
                {
                    "access": "public",
                    "arguments": [
                        {
                            "name": "frame",
                            "type": "QVideoFrame"
                        }
                    ],
                    "index": 10,
                    "name": "processFrame",
                    "returnType": "void"
                },
                {
                    "access": "private",
                    "index": 11,
                    "name": "updateDateTime",
                    "returnType": "void"
                },
                {
                    "access": "private",
                    "arguments": [
                        {
                            "name": "error",
                            "type": "QString"
                        }
                    ],
                    "index": 12,
                    "name": "handleCameraError",
                    "returnType": "void"
                }
            ],
            "superClasses": [
                {
                    "access": "public",
                    "name": "QObject"
                }
            ]
        }
    ],
    "inputFile": "QRScannerViewModel.h",
    "outputRevision": 68
}
